checkers/__init__.py
checkers/bot.py
checkers/field.py
checkers_bot-0.1.2.dist-info/METADATA
checkers_bot-0.1.2.dist-info/WHEEL
checkers_bot-0.1.2.dist-info/top_level.txt
checkers_bot-0.1.2.dist-info/RECORD
