Metadata-Version: 2.1
Name: checkers-bot
Version: 0.1.2
Summary: Checkers bot using min max alghoritm
Home-page: https://github.com/ruslan-ilesik/Checkers-bot
Author: lesikr
License: MIT
Keywords: checkers bot api game_api
Platform: UNKNOWN
Classifier: Development Status :: 3 - Alpha
Classifier: License :: OSI Approved :: MIT License
Classifier: Programming Language :: Python :: 3.8
